LICENSE
README.md
setup.py
ghsec_fib.egg-info/PKG-INFO
ghsec_fib.egg-info/SOURCES.txt
ghsec_fib.egg-info/dependency_links.txt
ghsec_fib.egg-info/entry_points.txt
ghsec_fib.egg-info/requires.txt
ghsec_fib.egg-info/top_level.txt
ghsec_fib_py/__init__.py
ghsec_fib_py/version.py
ghsec_fib_py/cmd/__init__.py
ghsec_fib_py/cmd/fib_numb.py
ghsec_fib_py/fib_calcs/__init__.py
ghsec_fib_py/fib_calcs/fib_number.py
ghsec_fib_py/fib_calcs/fib_numbers.py
tests/ghsec_fib_py/__init__.py
tests/ghsec_fib_py/test_fib_number.py
tests/ghsec_fib_py/test_fib_numbers.py