Metadata-Version: 2.1
Name: ghsec-fib
Version: 0.0.2
Summary: Calculates a Fibonacci number
Home-page: https://github.com/Kohelet/ghsec_fib
Author: ghsec
Author-email: security@griphands.tech
Classifier: Development Status :: 4 - Beta
Classifier: Programming Language :: Python :: 3
Classifier: Operating System :: OS Independent
Requires-Python: >=3.10
License-File: LICENSE
Requires-Dist: dill>=0.2.8
Provides-Extra: server
Requires-Dist: Flask>=1.0.0; extra == "server"
